CHANGES.txt
LICENSE.txt
MANIFEST.in
README.rst
compare.py
setup.py
compare.egg-info/PKG-INFO
compare.egg-info/SOURCES.txt
compare.egg-info/dependency_links.txt
compare.egg-info/not-zip-safe
compare.egg-info/top_level.txt
doc/Makefile
doc/conf.py
doc/conf.pyc
doc/core-api.rst
doc/core-matchers.rst
doc/index.rst
doc/make.bat
doc/releases.rst
doc/usage.rst
doc/_static/css/style.css
doc/_templates/layout.html