Metadata-Version: 1.0
Name: compare
Version: 0.2b
Summary: Alternative syntax for comparing/asserting expressions in Python. Supports pluggable matchers for custom comparisons.
Home-page: https://github.com/rudylattae/compare
Author: Rudy Lattae
Author-email: rudylattae@gmail.com
License: Simplified BSD
Keywords: python,compare,matcher,to be,to equal,assert,test equality,specification,BDD,TDD
Platform: UNKNOWN
Classifier: Development Status :: 4 - Beta
Classifier: Environment :: Console
Classifier: Intended Audience :: Developers
Classifier: License :: OSI Approved :: BSD License
Classifier: Operating System :: Microsoft :: Windows
Classifier: Programming Language :: Python
Classifier: Programming Language :: Python :: 2.7
